hashdd/__init__.py
hashdd/constants.py
hashdd/hashdd.py
hashdd/hashddcli.py
hashdd/utils.py
hashdd/algorithms/__init__.py
hashdd/algorithms/_sdbf_class.so
hashdd/algorithms/algorithm.py
hashdd/algorithms/hashdd_adler32.py
hashdd/algorithms/hashdd_content_hash.py
hashdd/algorithms/hashdd_crc32.py
hashdd/algorithms/hashdd_crc32b.py
hashdd/algorithms/hashdd_gost.py
hashdd/algorithms/hashdd_haval128.py
hashdd/algorithms/hashdd_haval160.py
hashdd/algorithms/hashdd_haval192.py
hashdd/algorithms/hashdd_haval224.py
hashdd/algorithms/hashdd_haval256.py
hashdd/algorithms/hashdd_md5.py
hashdd/algorithms/hashdd_md5w.py
hashdd/algorithms/hashdd_ripemd128.py
hashdd/algorithms/hashdd_ripemd256.py
hashdd/algorithms/hashdd_ripemd320.py
hashdd/algorithms/hashdd_sdhash.py
hashdd/algorithms/hashdd_sha1.py
hashdd/algorithms/hashdd_sha224.py
hashdd/algorithms/hashdd_sha256.py
hashdd/algorithms/hashdd_sha384.py
hashdd/algorithms/hashdd_sha3_224.py
hashdd/algorithms/hashdd_sha3_256.py
hashdd/algorithms/hashdd_sha3_384.py
hashdd/algorithms/hashdd_sha3_512.py
hashdd/algorithms/hashdd_sha512.py
hashdd/algorithms/hashdd_snefru128.py
hashdd/algorithms/hashdd_snefru256.py
hashdd/algorithms/hashdd_ssdeep.py
hashdd/algorithms/hashdd_tiger128.py
hashdd/algorithms/hashdd_tiger160.py
hashdd/algorithms/hashdd_tiger192.py
hashdd/algorithms/hashdd_tlsh.py
hashdd/algorithms/hashdd_whirlpool.py
hashdd/algorithms/sdbf_class.py
hashdd/algorithms/tlsh.so
hashdd/api/__init__.py
hashdd/api/client.py
hashdd/decompressor/__init__.py
hashdd/decompressor/decompressor.py
hashdd/decompressor/formats/__init__.py
hashdd/decompressor/formats/compressed_file.py
hashdd/decompressor/formats/compression.py
hashdd/decompressor/formats/zip_file.py
hashdd/features/__init__.py
hashdd/features/feature.py
hashdd/features/hashdd_children.py
hashdd/features/hashdd_file_absolute_path.py
hashdd/features/hashdd_file_name.py
hashdd/features/hashdd_filemagic.py
hashdd/features/hashdd_known_level.py
hashdd/features/hashdd_mime.py
hashdd-0.0.21.dist-info/LICENSE
hashdd-0.0.21.dist-info/LICENSE.py-mhash
hashdd-0.0.21.dist-info/METADATA
hashdd-0.0.21.dist-info/WHEEL
hashdd-0.0.21.dist-info/top_level.txt
hashdd-0.0.21.dist-info/RECORD
