Metadata-Version: 2.1
Name: hashdd
Version: 0.0.21
Summary: Official hashdd Python SDK
Home-page: https://www.hashdd.com
Author: hashdd
License: Apache License 2.0
Keywords: hashdd,pyhashdd,hash database
Platform: UNKNOWN
Classifier: Development Status :: 5 - Production/Stable
Classifier: Intended Audience :: Developers
Classifier: Programming Language :: Python
Classifier: Programming Language :: Python :: 3
Classifier: Programming Language :: Python :: Implementation :: CPython
Classifier: Programming Language :: Python :: Implementation :: PyPy
Classifier: Operating System :: OS Independent
Classifier: Operating System :: POSIX
Classifier: Operating System :: Microsoft :: Windows
Classifier: Operating System :: MacOS :: MacOS X
Classifier: Topic :: Software Development :: Libraries :: Python Modules
Requires-Python: >=3.7
Requires-Dist: bleach (==3.2.1)
Requires-Dist: certifi (==2020.6.20)
Requires-Dist: cffi (==1.14.3)
Requires-Dist: chardet (==3.0.4)
Requires-Dist: colorama (==0.4.3)
Requires-Dist: cryptography (==3.2)
Requires-Dist: docutils (==0.16)
Requires-Dist: idna (==2.10)
Requires-Dist: importlib-metadata (==2.0.0)
Requires-Dist: jeepney (==0.4.3)
Requires-Dist: keyring (==21.4.0)
Requires-Dist: numpy (==1.19.2)
Requires-Dist: packaging (==20.4)
Requires-Dist: Pillow (==7.2.0)
Requires-Dist: pkginfo (==1.5.0.1)
Requires-Dist: pybloomfiltermmap3 (==0.5.3)
Requires-Dist: pycparser (==2.20)
Requires-Dist: Pygments (==2.7.1)
Requires-Dist: pyparsing (==2.4.7)
Requires-Dist: pysha3 (==1.0.2)
Requires-Dist: python-magic (==0.4.18)
Requires-Dist: readme-renderer (==27.0)
Requires-Dist: requests (==2.24.0)
Requires-Dist: requests-toolbelt (==0.9.1)
Requires-Dist: rfc3986 (==1.4.0)
Requires-Dist: scipy (==1.5.2)
Requires-Dist: sdhash (==0.0.4)
Requires-Dist: SecretStorage (==3.1.2)
Requires-Dist: six (==1.15.0)
Requires-Dist: ssdeep (==3.4)
Requires-Dist: termcolor (==1.1.0)
Requires-Dist: tqdm (==4.50.2)
Requires-Dist: twine (==3.2.0)
Requires-Dist: urllib3 (==1.25.10)
Requires-Dist: webencodings (==0.5.1)
Requires-Dist: zipp (==3.3.0)
